leetcode_template/__init__.py
leetcode_template/generate_template.py
leetcode_template/script.py
leetcode_template/config/__init__.py
leetcode_template/config/template_config.py
leetcode_template/generators/__init__.py
leetcode_template/generators/generate_cmake.py
leetcode_template/generators/generate_header.py
leetcode_template/generators/generate_implementation.py
leetcode_template/generators/generate_tests.py
leetcode_template-0.1.3.dist-info/LICENSE
leetcode_template-0.1.3.dist-info/METADATA
leetcode_template-0.1.3.dist-info/WHEEL
leetcode_template-0.1.3.dist-info/entry_points.txt
leetcode_template-0.1.3.dist-info/top_level.txt
leetcode_template-0.1.3.dist-info/RECORD
