Metadata-Version: 2.1
Name: leetcode_template
Version: 0.1.3
Summary: Generate leetcode template
License: MIT License
Project-URL: Repository, https://github.com/MatchaOnMuffins/LeetcodeTemplate
Project-URL: Issues, https://github.com/MatchaOnMuffins/LeetcodeTemplate/issues
Classifier: Programming Language :: Python :: 3
Classifier: License :: OSI Approved :: MIT License
Classifier: Operating System :: OS Independent
Requires-Python: >=3.8
License-File: LICENSE
